Workbook
Name sub_annrnk: 'SUB-IP-EST2024-ANNRNK'!$A$4:$H$1939

Sheet SUB-IP-EST2024-ANNRNK
A1: table with row headers in column B and column headers in rows 3 through 4 (leading dots indicate sub-parts)
A2: Annual Estimates of the Resident Population for Incorporated Places of 20,000 or More, Ranked by July 1, 2024 Population: April 1, 2020 to July 1, 2024
A3: Rank | B3: Geographic Area | C3: April 1, 2020 Estimates Base | D3: Population Estimate (as of July 1)
D4: 2020 | E4: 2021 | F4: 2022 | G4: 2023 | H4: 2024 | I4: State | J4: City
A5: 1 | B5: New York city, New York | C5: 8805594 | D5: 8740306 | E5: 8453772 | F5: 8356179 | G5: 8390888 | H5: 8478072 | I5: =_xlfn.TEXTAFTER(B5,",") -> New York | J5: =_xlfn.TEXTBEFORE(B5,", ") -> New York city | K5: =IF(COUNTIF($I$5:I5,I5)=1,1,0) -> 1
A6: 2 | B6: Los Angeles city, California | C6: 3899449 | D6: 3896329 | E6: 3830987 | F6: 3832998 | G6: 3847428 | H6: 3878704 | I6: =_xlfn.TEXTAFTER(B6,",") -> California | J6: =_xlfn.TEXTBEFORE(B6,", ") -> Los Angeles city | K6: =IF(COUNTIF($I$5:I6,I6)=1,1,0) -> 1
A7: 3 | B7: Chicago city, Illinois | C7: 2748331 | D7: 2745196 | E7: 2706324 | F7: 2684076 | G7: 2699144 | H7: 2721308 | I7: =_xlfn.TEXTAFTER(B7,",") -> Illinois | J7: =_xlfn.TEXTBEFORE(B7,", ") -> Chicago city | K7: =IF(COUNTIF($I$5:I7,I7)=1,1,0) -> 1
A8: 4 | B8: Houston city, Texas | C8: 2300351 | D8: 2298945 | E8: 2291070 | F8: 2314258 | G8: 2346908 | H8: 2390125 | I8: =_xlfn.TEXTAFTER(B8,",") -> Texas | J8: =_xlfn.TEXTBEFORE(B8,", ") -> Houston city | K8: =IF(COUNTIF($I$5:I8,I8)=1,1,0) -> 1
A9: 5 | B9: Phoenix city, Arizona | C9: 1608415 | D9: 1612593 | E9: 1625132 | F9: 1644798 | G9: 1656231 | H9: 1673164 | I9: =_xlfn.TEXTAFTER(B9,",") -> Arizona | J9: =_xlfn.TEXTBEFORE(B9,", ") -> Phoenix city | K9: =IF(COUNTIF($I$5:I9,I9)=1,1,0) -> 1
A10: 6 | B10: Philadelphia city, Pennsylvania | C10: 1603794 | D10: 1600788 | E10: 1589918 | F10: 1570554 | G10: 1563349 | H10: 1573916 | I10: =_xlfn.TEXTAFTER(B10,",") -> Pennsylvania | J10: =_xlfn.TEXTBEFORE(B10,", ") -> Philadelphia city | K10: =IF(COUNTIF($I$5:I10,I10)=1,1,0) -> 1
A11: 7 | B11: San Antonio city, Texas | C11: 1434322 | D11: 1439340 | E11: 1454238 | F11: 1475931 | G11: 1502711 | H11: 1526656 | I11: =_xlfn.TEXTAFTER(B11,",") -> Texas | J11: =_xlfn.TEXTBEFORE(B11,", ") -> San Antonio city | K11: =IF(COUNTIF($I$5:I11,I11)=1,1,0) -> 0
A12: 8 | B12: San Diego city, California | C12: 1384429 | D12: 1384824 | E12: 1374972 | F12: 1388730 | G12: 1394555 | H12: 1404452 | I12: =_xlfn.TEXTAFTER(B12,",") -> California | J12: =_xlfn.TEXTBEFORE(B12,", ") -> San Diego city | K12: =IF(COUNTIF($I$5:I12,I12)=1,1,0) -> 0
A13: 9 | B13: Dallas city, Texas | C13: 1304345 | D13: 1303426 | E13: 1290070 | F13: 1303012 | G13: 1317163 | H13: 1326087 | I13: =_xlfn.TEXTAFTER(B13,",") -> Texas | J13: =_xlfn.TEXTBEFORE(B13,", ") -> Dallas city | K13: =IF(COUNTIF($I$5:I13,I13)=1,1,0) -> 0
A14: 10 | B14: Jacksonville city, Florida | C14: 949618 | D14: 951925 | E14: 957537 | F14: 975614 | G14: 993468 | H14: 1009833 | I14: =_xlfn.TEXTAFTER(B14,",") -> Florida | J14: =_xlfn.TEXTBEFORE(B14,", ") -> Jacksonville city | K14: =IF(COUNTIF($I$5:I14,I14)=1,1,0) -> 1
A15: 11 | B15: Fort Worth city, Texas | C15: 918923 | D15: 923645 | E15: 937692 | F15: 959520 | G15: 984664 | H15: 1008106 | I15: =_xlfn.TEXTAFTER(B15,",") -> Texas | J15: =_xlfn.TEXTBEFORE(B15,", ") -> Fort Worth city | K15: =IF(COUNTIF($I$5:I15,I15)=1,1,0) -> 0
A16: 12 | B16: San Jose city, California | C16: 1013419 | D16: 1009686 | E16: 981446 | F16: 978451 | G16: 983734 | H16: 997368 | I16: =_xlfn.TEXTAFTER(B16,",") -> California | J16: =_xlfn.TEXTBEFORE(B16,", ") -> San Jose city | K16: =IF(COUNTIF($I$5:I16,I16)=1,1,0) -> 0
... A1939: 1935 | B1939: Coronado city, California | C1939: 20199 | D1939: 20180 | E1939: 19257 | F1939: 18912 | G1939: 18657 | H1939: 18031 | I1939: =_xlfn.TEXTAFTER(B1939,",") -> California | J1939: =_xlfn.TEXTBEFORE(B1939,", ") -> Coronado city | K1939: =IF(COUNTIF($I$5:I1939,I1939)=1,1,0) -> 0
A1940: The Census Bureau has reviewed this data product to ensure appropriate access, use, and disclosure avoidance protection of the confidential source data used to produce this product (Data Management System (DMS) number: P-6000042 and P-7501659. Disclosure Review Board (DRB) approval number: CBDRB-FY25-0078). | I1940: =_xlfn.TEXTAFTER(B1940,",") -> #N/A | J1940: =_xlfn.TEXTBEFORE(B1940,", ") -> #N/A | K1940: =IF(COUNTIF($I$5:I1940,I1940)=1,1,0) -> 1
A1941: Note: An incorporated place is included if it had a population of 20,000 or more at any point during the time series. The rank is based on the July 1, 2024 population.The estimates are based on the 2020 Census and reflect changes to the April 1, 2020 population due to the Count Question Resolution and Post-Census Group Quarters Review programs, geographic program revisions, and the application of disclosure avoidance to protect confidentiality. For population estimates methodology statements, see https://www.census.gov/programs-surveys/popest/technical-documentation/methodology.html. All geographic boundaries for the 2024 population estimates series are as of January 1, 2024. For updates on Legal Boundary Change/Annexation Data, see https://www.census.gov/geographies/reference-files/time-series/geo/bas/annex.html. Additional information on these localities can be found in the Geographic Boundary Change Notes (see https://www.census.gov/programs-surveys/geography/technical-documentation/boundary-change-notes.html). | I1941: =_xlfn.TEXTAFTER(B1941,",") -> #N/A | J1941: =_xlfn.TEXTBEFORE(B1941,", ") -> #N/A | K1941: =IF(COUNTIF($I$5:I1941,I1941)=1,1,0) -> 0
A1942: Suggested Citation: | I1942: =_xlfn.TEXTAFTER(B1942,",") -> #N/A | J1942: =_xlfn.TEXTBEFORE(B1942,", ") -> #N/A | K1942: =IF(COUNTIF($I$5:I1942,I1942)=1,1,0) -> 0
A1943: Annual Estimates of the Resident Population for Incorporated Places of 20,000 or More, Ranked by July 1, 2024 Population: April 1, 2020 to July 1, 2024 (SUB-IP-EST2024-ANNRNK) | I1943: =_xlfn.TEXTAFTER(B1943,",") -> #N/A | J1943: =_xlfn.TEXTBEFORE(B1943,", ") -> #N/A | K1943: =IF(COUNTIF($I$5:I1943,I1943)=1,1,0) -> 0
A1944: Source: U.S. Census Bureau, Population Division | I1944: =_xlfn.TEXTAFTER(B1944,",") -> #N/A | J1944: =_xlfn.TEXTBEFORE(B1944,", ") -> #N/A | K1944: =IF(COUNTIF($I$5:I1944,I1944)=1,1,0) -> 0
A1945: Release Date: May 2025 | I1945: =_xlfn.TEXTAFTER(B1945,",") -> #N/A | J1945: =_xlfn.TEXTBEFORE(B1945,", ") -> #N/A | K1945: =IF(COUNTIF($I$5:I1945,I1945)=1,1,0) -> 0

Sheet CPI_Data
A1: State | B1: City Count | C1: {='SUB-IP-EST2024-ANNRNK'!I4:J4} -> State | D1: City | E1: Population | F1: Completed
A2: {=_xlfn._xlws.SORT(_xlfn.UNIQUE('SUB-IP-EST2024-ANNRNK'!$I$5:$I$1939))} -> Alabama | B2: =COUNTIF('SUB-IP-EST2024-ANNRNK'!$I$5:$I$1939,CPI_Data!A2) -> 33 | C2: {=_xlfn._xlws.SORT(_xlfn._xlws.FILTER('SUB-IP-EST2024-ANNRNK'!$I$5:$J$1939,'SUB-IP-EST2024-ANNRNK'!K5:K1939=1))} -> Alabama | D2: Huntsville city | E2: =_xlfn.XLOOKUP(CPI_Data!D2,'SUB-IP-EST2024-ANNRNK'!$J$5:$J$1939,'SUB-IP-EST2024-ANNRNK'!$F$5:$F$1939,"NA") -> 222299 | F2: FALSE
A3: Alaska | B3: =COUNTIF('SUB-IP-EST2024-ANNRNK'!$I$5:$I$1939,CPI_Data!A3) -> 3 | C3: Alaska | D3: Anchorage municipality | E3: =_xlfn.XLOOKUP(CPI_Data!D3,'SUB-IP-EST2024-ANNRNK'!$J$5:$J$1939,'SUB-IP-EST2024-ANNRNK'!$F$5:$F$1939,"NA") -> 287520 | F3: FALSE
A4: Arizona | B4: =COUNTIF('SUB-IP-EST2024-ANNRNK'!$I$5:$I$1939,CPI_Data!A4) -> 32 | C4: Arizona | D4: Phoenix city | E4: =_xlfn.XLOOKUP(CPI_Data!D4,'SUB-IP-EST2024-ANNRNK'!$J$5:$J$1939,'SUB-IP-EST2024-ANNRNK'!$F$5:$F$1939,"NA") -> 1644798 | F4: FALSE
A5: Arkansas | B5: =COUNTIF('SUB-IP-EST2024-ANNRNK'!$I$5:$I$1939,CPI_Data!A5) -> 25 | C5: Arkansas | D5: Little Rock city | E5: =_xlfn.XLOOKUP(CPI_Data!D5,'SUB-IP-EST2024-ANNRNK'!$J$5:$J$1939,'SUB-IP-EST2024-ANNRNK'!$F$5:$F$1939,"NA") -> 203416 | F5: FALSE
A6: California | B6: =COUNTIF('SUB-IP-EST2024-ANNRNK'!$I$5:$I$1939,CPI_Data!A6) -> 302 | C6: California | D6: Los Angeles city | E6: =_xlfn.XLOOKUP(CPI_Data!D6,'SUB-IP-EST2024-ANNRNK'!$J$5:$J$1939,'SUB-IP-EST2024-ANNRNK'!$F$5:$F$1939,"NA") -> 3832998 | F6: TRUE
A7: Colorado | B7: =COUNTIF('SUB-IP-EST2024-ANNRNK'!$I$5:$I$1939,CPI_Data!A7) -> 33 | C7: Colorado | D7: Denver city | E7: =_xlfn.XLOOKUP(CPI_Data!D7,'SUB-IP-EST2024-ANNRNK'!$J$5:$J$1939,'SUB-IP-EST2024-ANNRNK'!$F$5:$F$1939,"NA") -> 714851 | F7: FALSE
A8: Connecticut | B8: =COUNTIF('SUB-IP-EST2024-ANNRNK'!$I$5:$I$1939,CPI_Data!A8) -> 18 | C8: Connecticut | D8: Bridgeport city | E8: =_xlfn.XLOOKUP(CPI_Data!D8,'SUB-IP-EST2024-ANNRNK'!$J$5:$J$1939,'SUB-IP-EST2024-ANNRNK'!$F$5:$F$1939,"NA") -> 148552 | F8: FALSE
A9: Delaware | B9: =COUNTIF('SUB-IP-EST2024-ANNRNK'!$I$5:$I$1939,CPI_Data!A9) -> 4 | C9: Delaware | D9: Wilmington city | E9: =_xlfn.XLOOKUP(CPI_Data!D9,'SUB-IP-EST2024-ANNRNK'!$J$5:$J$1939,'SUB-IP-EST2024-ANNRNK'!$F$5:$F$1939,"NA") -> 121353 | F9: FALSE
A10: District of Columbia | B10: =COUNTIF('SUB-IP-EST2024-ANNRNK'!$I$5:$I$1939,CPI_Data!A10) -> 1 | C10: District of Columbia | D10: Washington city | E10: =_xlfn.XLOOKUP(CPI_Data!D10,'SUB-IP-EST2024-ANNRNK'!$J$5:$J$1939,'SUB-IP-EST2024-ANNRNK'!$F$5:$F$1939,"NA") -> 676725 | F10: FALSE
A11: Florida | B11: =COUNTIF('SUB-IP-EST2024-ANNRNK'!$I$5:$I$1939,CPI_Data!A11) -> 120 | C11: Florida | D11: Jacksonville city | E11: =_xlfn.XLOOKUP(CPI_Data!D11,'SUB-IP-EST2024-ANNRNK'!$J$5:$J$1939,'SUB-IP-EST2024-ANNRNK'!$F$5:$F$1939,"NA") -> 975614 | F11: FALSE
A12: Georgia | B12: =COUNTIF('SUB-IP-EST2024-ANNRNK'!$I$5:$I$1939,CPI_Data!A12) -> 59 | C12: Georgia | D12: Atlanta city | E12: =_xlfn.XLOOKUP(CPI_Data!D12,'SUB-IP-EST2024-ANNRNK'!$J$5:$J$1939,'SUB-IP-EST2024-ANNRNK'!$F$5:$F$1939,"NA") -> 500249 | F12: FALSE
A13: Hawaii | B13: =COUNTIF('SUB-IP-EST2024-ANNRNK'!$I$5:$I$1939,CPI_Data!A13) -> 1 | C13: Hawaii | D13: Urban Honolulu CDP | E13: =_xlfn.XLOOKUP(CPI_Data!D13,'SUB-IP-EST2024-ANNRNK'!$J$5:$J$1939,'SUB-IP-EST2024-ANNRNK'!$F$5:$F$1939,"NA") -> 343974 | F13: FALSE
A14: Idaho | B14: =COUNTIF('SUB-IP-EST2024-ANNRNK'!$I$5:$I$1939,CPI_Data!A14) -> 15 | C14: Idaho | D14: Boise City city | E14: =_xlfn.XLOOKUP(CPI_Data!D14,'SUB-IP-EST2024-ANNRNK'!$J$5:$J$1939,'SUB-IP-EST2024-ANNRNK'!$F$5:$F$1939,"NA") -> 237614 | F14: FALSE
... A52: Wyoming | B52: =COUNTIF('SUB-IP-EST2024-ANNRNK'!$I$5:$I$1939,CPI_Data!A52) -> 5 | C52: Wyoming | D52: Cheyenne city | E52: =_xlfn.XLOOKUP(CPI_Data!D52,'SUB-IP-EST2024-ANNRNK'!$J$5:$J$1939,'SUB-IP-EST2024-ANNRNK'!$F$5:$F$1939,"NA") -> 64668 | F52: FALSE

Sheet myStates
A1: Count | B1: StateAbb | C1: State | D1: City/Location
A2: 1 | B2: AZ | C2: ='SUB-IP-EST2024-ANNRNK'!I9 -> Arizona | D2: =_xlfn.XLOOKUP(C2,CPI_Data!$C$2:$C$52,CPI_Data!$D$2:$D$52) -> Phoenix city
A3: 2 | B3: CA | C3: ='SUB-IP-EST2024-ANNRNK'!I12 -> California | D3: =_xlfn.XLOOKUP(C3,CPI_Data!$C$2:$C$52,CPI_Data!$D$2:$D$52) -> Los Angeles city
A4: 3 | B4: FL | C4: ='SUB-IP-EST2024-ANNRNK'!I14 -> Florida | D4: =_xlfn.XLOOKUP(C4,CPI_Data!$C$2:$C$52,CPI_Data!$D$2:$D$52) -> Jacksonville city
A5: 4 | B5: IL | C5: ='SUB-IP-EST2024-ANNRNK'!I7 -> Illinois | D5: =_xlfn.XLOOKUP(C5,CPI_Data!$C$2:$C$52,CPI_Data!$D$2:$D$52) -> Chicago city
A6: 5 | B6: MI | C6: ='SUB-IP-EST2024-ANNRNK'!I30 -> Michigan | D6: =_xlfn.XLOOKUP(C6,CPI_Data!$C$2:$C$52,CPI_Data!$D$2:$D$52) -> Detroit city
A7: 6 | B7: NJ | C7: ='SUB-IP-EST2024-ANNRNK'!I68 -> New Jersey | D7: =_xlfn.XLOOKUP(C7,CPI_Data!$C$2:$C$52,CPI_Data!$D$2:$D$52) -> Newark city
A8: 7 | B8: NV | C8: ='SUB-IP-EST2024-ANNRNK'!I28 -> Nevada | D8: =_xlfn.XLOOKUP(C8,CPI_Data!$C$2:$C$52,CPI_Data!$D$2:$D$52) -> Las Vegas city
A9: 8 | B9: NY | C9: ='SUB-IP-EST2024-ANNRNK'!I5 -> New York | D9: =_xlfn.XLOOKUP(C9,CPI_Data!$C$2:$C$52,CPI_Data!$D$2:$D$52) -> New York city
A10: 9 | B10: OH | C10: ='SUB-IP-EST2024-ANNRNK'!I19 -> Ohio | D10: =_xlfn.XLOOKUP(C10,CPI_Data!$C$2:$C$52,CPI_Data!$D$2:$D$52) -> Columbus city
A11: 10 | B11: PA | C11: ='SUB-IP-EST2024-ANNRNK'!I10 -> Pennsylvania | D11: =_xlfn.XLOOKUP(C11,CPI_Data!$C$2:$C$52,CPI_Data!$D$2:$D$52) -> Philadelphia city
A12: 11 | B12: TX | C12: ='SUB-IP-EST2024-ANNRNK'!I8 -> Texas | D12: =_xlfn.XLOOKUP(C12,CPI_Data!$C$2:$C$52,CPI_Data!$D$2:$D$52) -> Houston city
